<!DOCTYPE suite SYSTEM "https://testng.org/testng-1.0.dtd" >
<suite name="Ass06AmazonSearchTestwithParameters">
<test name="All Test Suite">
    <parameter name="keyword" value="Java"/>
    <classes>
        <class name="com.SDA.mentoring.HW.Ass06AmazonSearchTestwithParameters"></class>
    </classes>
</test>

    <test name="SearchSeleniumTest">
        <parameter name="keyword" value="Selenium"/>
        <classes>
            <class name="com.SDA.mentoring.HW.Ass06AmazonSearchTestwithParameters"></class>
        </classes>
    </test>


</suite>